tablegpt_executor_client/__init__.py
tablegpt_executor_client/client.py
tablegpt_executor_client/errors.py
tablegpt_executor_client/schemas.py
tablegpt_executor-0.1.3.dist-info/METADATA
tablegpt_executor-0.1.3.dist-info/WHEEL
tablegpt_executor-0.1.3.dist-info/top_level.txt
tablegpt_executor-0.1.3.dist-info/RECORD
