Metadata-Version: 2.1
Name: tablegpt-executor
Version: 0.1.3
Summary: Tablegpt executor python client
Author-email: saf <saf@zjuici.com>, jlzhou <jlzhou@zjuici.com>
License: MIT
Requires-Python: <3.12,>=3.10
Requires-Dist: requests >=2.31.0
Requires-Dist: aiohttp >=3.8.6
Requires-Dist: pydantic <3.0.0,>=2.0.0
